{"mean":{"confidence_interval":{"confidence_level":0.95,"lower_bound":30458275.797335647,"upper_bound":31776698.961666666},"point_estimate":31122509.188981485,"standard_error":336495.6036014819},"median":{"confidence_interval":{"confidence_level":0.95,"lower_bound":30012870.37037037,"upper_bound":31775004.266666666},"point_estimate":31344217.3125,"standard_error":370887.92051990435},"median_abs_dev":{"confidence_interval":{"confidence_level":0.95,"lower_bound":42761.7353033256,"upper_bound":2078021.705096634},"point_estimate":719939.2362160239,"standard_error":607360.8110368457},"slope":{"confidence_interval":{"confidence_level":0.95,"lower_bound":30458419.545193397,"upper_bound":31926542.989327706},"point_estimate":31258692.493506495,"standard_error":383020.69836171804},"std_dev":{"confidence_interval":{"confidence_level":0.95,"lower_bound":576962.3946633195,"upper_bound":1466315.6916131095},"point_estimate":1121045.4380146125,"standard_error":225364.65060802564}}