{"mean":{"confidence_interval":{"confidence_level":0.95,"lower_bound":27082622.981032737,"upper_bound":27638089.24423611},"point_estimate":27410820.423878968,"standard_error":147168.47555666263},"median":{"confidence_interval":{"confidence_level":0.95,"lower_bound":27315661.46875,"upper_bound":27684690.836805556},"point_estimate":27605096.175,"standard_error":104792.76403688226},"median_abs_dev":{"confidence_interval":{"confidence_level":0.95,"lower_bound":28835.60579806787,"upper_bound":471210.33889934473},"point_estimate":162335.0138867274,"standard_error":120722.46818984384},"slope":{"confidence_interval":{"confidence_level":0.95,"lower_bound":26935999.978561766,"upper_bound":27661382.6778481},"point_estimate":27399403.11883117,"standard_error":195534.5914876543},"std_dev":{"confidence_interval":{"confidence_level":0.95,"lower_bound":100915.1710199142,"upper_bound":724373.8182135003},"point_estimate":488952.8886297149,"standard_error":189563.18925868825}}