{"mean":{"confidence_interval":{"confidence_level":0.95,"lower_bound":1420444.200311246,"upper_bound":1443250.8735504835},"point_estimate":1431486.8199697766,"standard_error":5820.919184471808},"median":{"confidence_interval":{"confidence_level":0.95,"lower_bound":1440783.5,"upper_bound":1455223.8692743764},"point_estimate":1452441.410330948,"standard_error":3977.3057686209872},"median_abs_dev":{"confidence_interval":{"confidence_level":0.95,"lower_bound":10819.866424915906,"upper_bound":39639.66104249729},"point_estimate":18599.090681313217,"standard_error":7793.034598280555},"slope":{"confidence_interval":{"confidence_level":0.95,"lower_bound":1427448.8758298017,"upper_bound":1450568.4936149884},"point_estimate":1439127.627202601,"standard_error":5924.15000296754},"std_dev":{"confidence_interval":{"confidence_level":0.95,"lower_bound":43768.04490957081,"upper_bound":74282.77270931783},"point_estimate":58339.41825365597,"standard_error":8077.527719486756}}