{"mean":{"confidence_interval":{"confidence_level":0.95,"lower_bound":33392993.952916663,"upper_bound":34175459.37222222},"point_estimate":33802661.81222222,"standard_error":200316.08984187033},"median":{"confidence_interval":{"confidence_level":0.95,"lower_bound":33278484.5,"upper_bound":34209622.2},"point_estimate":33925210.083333336,"standard_error":195946.09459292737},"median_abs_dev":{"confidence_interval":{"confidence_level":0.95,"lower_bound":56524.98884648453,"upper_bound":1232241.3056900091},"point_estimate":427328.55491340347,"standard_error":286685.17370820895},"slope":{"confidence_interval":{"confidence_level":0.95,"lower_bound":33091148.053257268,"upper_bound":33983747.58032128},"point_estimate":33575117.967965364,"standard_error":236243.15466927417},"std_dev":{"confidence_interval":{"confidence_level":0.95,"lower_bound":273138.32789962454,"upper_bound":859187.9368023943},"point_estimate":666969.6184591851,"standard_error":144966.06368677967}}