{"mean":{"confidence_interval":{"confidence_level":0.95,"lower_bound":13358719272.42,"upper_bound":13394320417.42},"point_estimate":13376025095.7,"standard_error":9137818.699617472},"median":{"confidence_interval":{"confidence_level":0.95,"lower_bound":13351256916.0,"upper_bound":13398706124.5},"point_estimate":13370197812.5,"standard_error":13029321.361792233},"median_abs_dev":{"confidence_interval":{"confidence_level":0.95,"lower_bound":3719442.2906666994,"upper_bound":49073720.354667306},"point_estimate":38036132.71802366,"standard_error":12631481.277474867},"slope":null,"std_dev":{"confidence_interval":{"confidence_level":0.95,"lower_bound":17362828.820065107,"upper_bound":38778384.68999741},"point_estimate":30462601.432515286,"standard_error":5590147.943886876}}