{"mean":{"confidence_interval":{"confidence_level":0.95,"lower_bound":603.8048752418924,"upper_bound":609.3162363002378},"point_estimate":606.666093920654,"standard_error":1.404971015636928},"median":{"confidence_interval":{"confidence_level":0.95,"lower_bound":607.3102721524787,"upper_bound":610.6637105072809},"point_estimate":608.5730774017611,"standard_error":1.0751499745842281},"median_abs_dev":{"confidence_interval":{"confidence_level":0.95,"lower_bound":5.0694423707183445,"upper_bound":8.603541328038725},"point_estimate":6.497841966560876,"standard_error":0.9023530645562843},"slope":{"confidence_interval":{"confidence_level":0.95,"lower_bound":598.4433803305752,"upper_bound":606.7900079125185},"point_estimate":602.7599914841608,"standard_error":2.1307741874223654},"std_dev":{"confidence_interval":{"confidence_level":0.95,"lower_bound":10.525910796337454,"upper_bound":17.07254656603537},"point_estimate":14.101284890043928,"standard_error":1.671770756822926}}