{"mean":{"confidence_interval":{"confidence_level":0.95,"lower_bound":1437884.196300409,"upper_bound":1456421.7816886345},"point_estimate":1447289.0786421583,"standard_error":4725.036401557789},"median":{"confidence_interval":{"confidence_level":0.95,"lower_bound":1453435.78,"upper_bound":1457038.750295683},"point_estimate":1455390.6928152493,"standard_error":895.55170868951},"median_abs_dev":{"confidence_interval":{"confidence_level":0.95,"lower_bound":7338.083704255874,"upper_bound":15938.406764289355},"point_estimate":10293.165803724223,"standard_error":2195.803820794163},"slope":{"confidence_interval":{"confidence_level":0.95,"lower_bound":1433637.0621754052,"upper_bound":1456133.2779789513},"point_estimate":1445434.0203546623,"standard_error":5747.370622826787},"std_dev":{"confidence_interval":{"confidence_level":0.95,"lower_bound":38310.86557136828,"upper_bound":55176.41395671357},"point_estimate":47467.14158736276,"standard_error":4294.6465055898725}}